[{"key":"feedback.json","value":"[\n  {\n    \"id\": \"fb-mqogon1q\",\n    \"page\": \"/ship-test\",\n    \"category\": \"ux\",\n    \"message\": \"Ship phase smoke test submission\",\n    \"timestamp\": \"2026-06-22T00:12:42.542Z\"\n  },\n  {\n    \"id\": \"fb-mqohhw0y\",\n    \"page\": \"/ship-test\",\n    \"category\": \"ux\",\n    \"message\": \"Ship phase smoke test submission\",\n    \"timestamp\": \"2026-06-22T00:35:27.202Z\"\n  },\n  {\n    \"id\": \"fb-mqojxy1p\",\n    \"page\": \"/ship-test\",\n    \"category\": \"ux\",\n    \"message\": \"Ship phase smoke test submission\",\n    \"timestamp\": \"2026-06-22T01:43:55.549Z\"\n  },\n  {\n    \"id\": \"fb-mqok7bf1\",\n    \"page\": \"/ship-test\",\n    \"category\": \"ux\",\n    \"message\": \"Ship phase smoke test submission\",\n    \"timestamp\": \"2026-06-22T01:51:12.781Z\"\n  },\n  {\n    \"id\": \"fb-mqolrw5b\",\n    \"page\": \"/ship-test\",\n    \"category\": \"ux\",\n    \"message\": \"Ship phase smoke test submission\",\n    \"timestamp\": \"2026-06-22T02:35:12.383Z\"\n  },\n  {\n    \"id\": \"fb-mqolz4u1\",\n    \"page\": \"/ship-test\",\n    \"category\": \"ux\",\n    \"message\": \"Ship phase smoke test submission\",\n    \"timestamp\": \"2026-06-22T02:40:50.233Z\"\n  },\n  {\n    \"id\": \"fb-mqom0b6f\",\n    \"page\": \"/ship-test\",\n    \"category\": \"ux\",\n    \"message\": \"Ship phase smoke test submission\",\n    \"timestamp\": \"2026-06-22T02:41:45.111Z\"\n  }\n]"},{"key":"mirror-executions.json","value":"[\n  {\n    \"id\": \"ex-mqom0k4f-it91\",\n    \"mirrorId\": \"mirror-mqohhw1k\",\n    \"userAddress\": \"0xSmokeTest000000000000000000000000000001\",\n    \"alphaWallet\": \"0x7a3f8c2e1b9d4a6f0e8c5b2d1a9f7e4c3b8a6d5e1\",\n    \"chain\": \"base\",\n    \"mode\": \"paper\",\n    \"queueId\": \"mq-demo001\",\n    \"tradeUsd\": 100,\n    \"pnlUsd\": -2.12,\n    \"platformFeeUsd\": 0,\n    \"timestamp\": \"2026-06-22T02:41:56.703Z\",\n    \"status\": \"simulated\"\n  },\n  {\n    \"id\": \"ex-mqom0k4g-pzf4\",\n    \"mirrorId\": \"mirror-mqoj5n3w\",\n    \"userAddress\": \"0x1A3Fb6EEbee78003d0140ebD4B46Fe0ebd22C45c\",\n    \"alphaWallet\": \"0x7a3f8c2e1b9d4a6f0e8c5b2d1a9f7e4c3b8a6d5e1\",\n    \"chain\": \"base\",\n    \"mode\": \"paper\",\n    \"queueId\": \"mq-demo001\",\n    \"tradeUsd\": 1,\n    \"pnlUsd\": -0.02,\n    \"platformFeeUsd\": 0,\n    \"timestamp\": \"2026-06-22T02:41:56.704Z\",\n    \"status\": \"simulated\"\n  },\n  {\n    \"id\": \"ex-mqom0k4g-mq1y\",\n    \"mirrorId\": \"mirror-mqojxy34\",\n    \"userAddress\": \"0xSmokeTest000000000000000000000000000001\",\n    \"alphaWallet\": \"0x7a3f8c2e1b9d4a6f0e8c5b2d1a9f7e4c3b8a6d5e1\",\n    \"chain\": \"base\",\n    \"mode\": \"paper\",\n    \"queueId\": \"mq-demo001\",\n    \"tradeUsd\": 100,\n    \"pnlUsd\": 9.78,\n    \"platformFeeUsd\": 0,\n    \"timestamp\": \"2026-06-22T02:41:56.704Z\",\n    \"status\": \"simulated\"\n  },\n  {\n    \"id\": \"ex-mqom0k4g-kfet\",\n    \"mirrorId\": \"mirror-mqok2dfh\",\n    \"userAddress\": \"0x1A3Fb6EEbee78003d0140ebD4B46Fe0ebd22C45c\",\n    \"alphaWallet\": \"0x7a3f8c2e1b9d4a6f0e8c5b2d1a9f7e4c3b8a6d5e1\",\n    \"chain\": \"base\",\n    \"mode\": \"paper\",\n    \"queueId\": \"mq-demo001\",\n    \"tradeUsd\": 0.2,\n    \"pnlUsd\": 0.02,\n    \"platformFeeUsd\": 0,\n    \"timestamp\": \"2026-06-22T02:41:56.704Z\",\n    \"status\": \"simulated\"\n  },\n  {\n    \"id\": \"ex-mqom0k4g-6qth\",\n    \"mirrorId\": \"mirror-mqok7bfr\",\n    \"userAddress\": \"0xSmokeTest000000000000000000000000000001\",\n    \"alphaWallet\": \"0x7a3f8c2e1b9d4a6f0e8c5b2d1a9f7e4c3b8a6d5e1\",\n    \"chain\": \"base\",\n    \"mode\": \"paper\",\n    \"queueId\": \"mq-demo001\",\n    \"tradeUsd\": 100,\n    \"pnlUsd\": 15.26,\n    \"platformFeeUsd\": 0,\n    \"timestamp\": \"2026-06-22T02:41:56.704Z\",\n    \"status\": \"simulated\"\n  },\n  {\n    \"id\": \"ex-mqom0k4g-avs4\",\n    \"mirrorId\": \"mirror-mqokalkn\",\n    \"userAddress\": \"0x1A3Fb6EEbee78003d0140ebD4B46Fe0ebd22C45c\",\n    \"alphaWallet\": \"0x7a3f8c2e1b9d4a6f0e8c5b2d1a9f7e4c3b8a6d5e1\",\n    \"chain\": \"base\",\n    \"mode\": \"paper\",\n    \"queueId\": \"mq-demo001\",\n    \"tradeUsd\": 100,\n    \"pnlUsd\": 12.9,\n    \"platformFeeUsd\": 0,\n    \"timestamp\": \"2026-06-22T02:41:56.704Z\",\n    \"status\": \"simulated\"\n  },\n  {\n    \"id\": \"ex-mqom0k4h-35dx\",\n    \"mirrorId\": \"mirror-mqolrw69\",\n    \"userAddress\": \"0xSmokeTest000000000000000000000000000001\",\n    \"alphaWallet\": \"0x7a3f8c2e1b9d4a6f0e8c5b2d1a9f7e4c3b8a6d5e1\",\n    \"chain\": \"base\",\n    \"mode\": \"paper\",\n    \"queueId\": \"mq-demo001\",\n    \"tradeUsd\": 100,\n    \"pnlUsd\": 11.25,\n    \"platformFeeUsd\": 0,\n    \"timestamp\": \"2026-06-22T02:41:56.705Z\",\n    \"status\": \"simulated\"\n  },\n  {\n    \"id\": \"ex-mqom0k4h-1i1z\",\n    \"mirrorId\": \"mirror-mqolz4ui\",\n    \"userAddress\": \"0xSmokeTest000000000000000000000000000001\",\n    \"alphaWallet\": \"0x7a3f8c2e1b9d4a6f0e8c5b2d1a9f7e4c3b8a6d5e1\",\n    \"chain\": \"base\",\n    \"mode\": \"paper\",\n    \"queueId\": \"mq-demo001\",\n    \"tradeUsd\": 100,\n    \"pnlUsd\": -7.5,\n    \"platformFeeUsd\": 0,\n    \"timestamp\": \"2026-06-22T02:41:56.705Z\",\n    \"status\": \"simulated\"\n  },\n  {\n    \"id\": \"ex-mqom0k4h-vaj8\",\n    \"mirrorId\": \"mirror-mqom0b6y\",\n    \"userAddress\": \"0xSmokeTest000000000000000000000000000001\",\n    \"alphaWallet\": \"0x7a3f8c2e1b9d4a6f0e8c5b2d1a9f7e4c3b8a6d5e1\",\n    \"chain\": \"base\",\n    \"mode\": \"paper\",\n    \"queueId\": \"mq-demo001\",\n    \"tradeUsd\": 100,\n    \"pnlUsd\": 15.74,\n    \"platformFeeUsd\": 0,\n    \"timestamp\": \"2026-06-22T02:41:56.705Z\",\n    \"status\": \"simulated\"\n  }\n]"},{"key":"mirror-queue.json","value":"[\n  {\n    \"id\": \"mq-demo001\",\n    \"alphaWallet\": \"0x7a3f8c2e1b9d4a6f0e8c5b2d1a9f7e4c3b8a6d5e1\",\n    \"chain\": \"base\",\n    \"newTransfers\": 2,\n    \"timestamp\": \"2026-06-22T12:00:00.000Z\",\n    \"status\": \"simulated\"\n  }\n]"},{"key":"mirrors.json","value":"[\n  {\n    \"id\": \"mirror-mqogonoi\",\n    \"userAddress\": \"0xSmokeTest000000000000000000000000000001\",\n    \"alphaWallet\": \"0x7A3f8C2e1b9d4a6f0e8c5B2D1A9f7e4C3b8A6D5e\",\n    \"status\": \"active\",\n    \"mode\": \"paper\",\n    \"perTradeCapUsd\": 500,\n    \"dailyCapUsd\": 2000,\n    \"userRatioPct\": 10,\n    \"allowedChains\": [\n      \"base\",\n      \"arbitrum\"\n    ],\n    \"denylistTokens\": [],\n    \"createdAt\": \"2026-06-22T00:12:43.362Z\"\n  },\n  {\n    \"id\": \"mirror-mqohhw1k\",\n    \"userAddress\": \"0xSmokeTest000000000000000000000000000001\",\n    \"alphaWallet\": \"0x7A3f8C2e1b9d4a6f0e8c5B2D1A9f7e4C3b8A6D5e\",\n    \"status\": \"active\",\n    \"mode\": \"paper\",\n    \"perTradeCapUsd\": 500,\n    \"dailyCapUsd\": 2000,\n    \"userRatioPct\": 10,\n    \"allowedChains\": [\n      \"base\",\n      \"arbitrum\"\n    ],\n    \"denylistTokens\": [],\n    \"createdAt\": \"2026-06-22T00:35:27.224Z\"\n  },\n  {\n    \"id\": \"mirror-mqoj5n3w\",\n    \"userAddress\": \"0x1A3Fb6EEbee78003d0140ebD4B46Fe0ebd22C45c\",\n    \"alphaWallet\": \"0x7A3f8C2e1b9d4a6f0e8c5B2D1A9f7e4C3b8A6D5e\",\n    \"status\": \"active\",\n    \"mode\": \"paper\",\n    \"perTradeCapUsd\": 1,\n    \"dailyCapUsd\": 100,\n    \"userRatioPct\": 100,\n    \"allowedChains\": [\n      \"base\",\n      \"arbitrum\",\n      \"ethereum\"\n    ],\n    \"denylistTokens\": [],\n    \"createdAt\": \"2026-06-22T01:21:55.004Z\"\n  },\n  {\n    \"id\": \"mirror-mqojxy34\",\n    \"userAddress\": \"0xSmokeTest000000000000000000000000000001\",\n    \"alphaWallet\": \"0x7A3f8C2e1b9d4a6f0e8c5B2D1A9f7e4C3b8A6D5e\",\n    \"status\": \"active\",\n    \"mode\": \"paper\",\n    \"perTradeCapUsd\": 500,\n    \"dailyCapUsd\": 2000,\n    \"userRatioPct\": 10,\n    \"allowedChains\": [\n      \"base\",\n      \"arbitrum\"\n    ],\n    \"denylistTokens\": [],\n    \"createdAt\": \"2026-06-22T01:43:55.600Z\"\n  },\n  {\n    \"id\": \"mirror-mqok2dfh\",\n    \"userAddress\": \"0x1A3Fb6EEbee78003d0140ebD4B46Fe0ebd22C45c\",\n    \"alphaWallet\": \"0x7A3f8C2e1b9d4a6f0e8c5B2D1A9f7e4C3b8A6D5e\",\n    \"status\": \"active\",\n    \"mode\": \"paper\",\n    \"perTradeCapUsd\": 1,\n    \"dailyCapUsd\": 50,\n    \"userRatioPct\": 10,\n    \"allowedChains\": [\n      \"base\",\n      \"arbitrum\",\n      \"ethereum\"\n    ],\n    \"denylistTokens\": [],\n    \"createdAt\": \"2026-06-22T01:47:22.109Z\"\n  },\n  {\n    \"id\": \"mirror-mqok7bfr\",\n    \"userAddress\": \"0xSmokeTest000000000000000000000000000001\",\n    \"alphaWallet\": \"0x7A3f8C2e1b9d4a6f0e8c5B2D1A9f7e4C3b8A6D5e\",\n    \"status\": \"active\",\n    \"mode\": \"paper\",\n    \"perTradeCapUsd\": 500,\n    \"dailyCapUsd\": 2000,\n    \"userRatioPct\": 10,\n    \"allowedChains\": [\n      \"base\",\n      \"arbitrum\"\n    ],\n    \"denylistTokens\": [],\n    \"createdAt\": \"2026-06-22T01:51:12.807Z\"\n  },\n  {\n    \"id\": \"mirror-mqokalkn\",\n    \"userAddress\": \"0x1A3Fb6EEbee78003d0140ebD4B46Fe0ebd22C45c\",\n    \"alphaWallet\": \"0x7A3f8C2e1b9d4a6f0e8c5B2D1A9f7e4C3b8A6D5e\",\n    \"status\": \"active\",\n    \"mode\": \"paper\",\n    \"perTradeCapUsd\": 500,\n    \"dailyCapUsd\": 2000,\n    \"userRatioPct\": 10,\n    \"allowedChains\": [\n      \"base\",\n      \"arbitrum\",\n      \"ethereum\"\n    ],\n    \"denylistTokens\": [],\n    \"createdAt\": \"2026-06-22T01:53:45.911Z\"\n  },\n  {\n    \"id\": \"mirror-mqolrw69\",\n    \"userAddress\": \"0xSmokeTest000000000000000000000000000001\",\n    \"alphaWallet\": \"0x7A3f8C2e1b9d4a6f0e8c5B2D1A9f7e4C3b8A6D5e\",\n    \"status\": \"active\",\n    \"mode\": \"paper\",\n    \"perTradeCapUsd\": 500,\n    \"dailyCapUsd\": 2000,\n    \"userRatioPct\": 10,\n    \"allowedChains\": [\n      \"base\",\n      \"arbitrum\"\n    ],\n    \"denylistTokens\": [],\n    \"createdAt\": \"2026-06-22T02:35:12.417Z\"\n  },\n  {\n    \"id\": \"mirror-mqolz4ui\",\n    \"userAddress\": \"0xSmokeTest000000000000000000000000000001\",\n    \"alphaWallet\": \"0x7A3f8C2e1b9d4a6f0e8c5B2D1A9f7e4C3b8A6D5e\",\n    \"status\": \"active\",\n    \"mode\": \"paper\",\n    \"perTradeCapUsd\": 500,\n    \"dailyCapUsd\": 2000,\n    \"userRatioPct\": 10,\n    \"allowedChains\": [\n      \"base\",\n      \"arbitrum\"\n    ],\n    \"denylistTokens\": [],\n    \"createdAt\": \"2026-06-22T02:40:50.250Z\"\n  },\n  {\n    \"id\": \"mirror-mqom0b6y\",\n    \"userAddress\": \"0xSmokeTest000000000000000000000000000001\",\n    \"alphaWallet\": \"0x7A3f8C2e1b9d4a6f0e8c5B2D1A9f7e4C3b8A6D5e\",\n    \"status\": \"active\",\n    \"mode\": \"paper\",\n    \"perTradeCapUsd\": 500,\n    \"dailyCapUsd\": 2000,\n    \"userRatioPct\": 10,\n    \"allowedChains\": [\n      \"base\",\n      \"arbitrum\"\n    ],\n    \"denylistTokens\": [],\n    \"createdAt\": \"2026-06-22T02:41:45.130Z\"\n  },\n  {\n    \"id\": \"mirror-mqonvwdi\",\n    \"userAddress\": \"0x1A3Fb6EEbee78003d0140ebD4B46Fe0ebd22C45c\",\n    \"alphaWallet\": \"0x7A3f8C2e1b9d4a6f0e8c5B2D1A9f7e4C3b8A6D5e\",\n    \"status\": \"paused\",\n    \"mode\": \"live\",\n    \"perTradeCapUsd\": 1,\n    \"dailyCapUsd\": 10,\n    \"userRatioPct\": 10,\n    \"allowedChains\": [\n      \"base\",\n      \"arbitrum\",\n      \"ethereum\"\n    ],\n    \"denylistTokens\": [],\n    \"createdAt\": \"2026-06-22T03:34:18.534Z\"\n  },\n  {\n    \"id\": \"mirror-mqoo968y\",\n    \"userAddress\": \"0x1A3Fb6EEbee78003d0140ebD4B46Fe0ebd22C45c\",\n    \"alphaWallet\": \"0x7A3f8C2e1b9d4a6f0e8c5B2D1A9f7e4C3b8A6D5e\",\n    \"status\": \"paused\",\n    \"mode\": \"live\",\n    \"perTradeCapUsd\": 1,\n    \"dailyCapUsd\": 5,\n    \"userRatioPct\": 5,\n    \"allowedChains\": [\n      \"base\",\n      \"arbitrum\",\n      \"ethereum\"\n    ],\n    \"denylistTokens\": [],\n    \"createdAt\": \"2026-06-22T03:44:37.858Z\"\n  },\n  {\n    \"id\": \"mirror-mqoqxasa\",\n    \"userAddress\": \"0x1A3Fb6EEbee78003d0140ebD4B46Fe0ebd22C45c\",\n    \"alphaWallet\": \"0x7A3f8C2e1b9d4a6f0e8c5B2D1A9f7e4C3b8A6D5e\",\n    \"status\": \"active\",\n    \"mode\": \"live\",\n    \"perTradeCapUsd\": 1,\n    \"dailyCapUsd\": 5,\n    \"userRatioPct\": 5,\n    \"allowedChains\": [\n      \"base\",\n      \"arbitrum\",\n      \"ethereum\"\n    ],\n    \"denylistTokens\": [],\n    \"createdAt\": \"2026-06-22T04:59:22.714Z\"\n  },\n  {\n    \"id\": \"mirror-mqoqzkft\",\n    \"userAddress\": \"0x1A3Fb6EEbee78003d0140ebD4B46Fe0ebd22C45c\",\n    \"alphaWallet\": \"0x7A3f8C2e1b9d4a6f0e8c5B2D1A9f7e4C3b8A6D5e\",\n    \"status\": \"paused\",\n    \"mode\": \"live\",\n    \"perTradeCapUsd\": 2,\n    \"dailyCapUsd\": 5,\n    \"userRatioPct\": 2,\n    \"allowedChains\": [\n      \"base\",\n      \"arbitrum\",\n      \"ethereum\"\n    ],\n    \"denylistTokens\": [],\n    \"createdAt\": \"2026-06-22T05:01:08.537Z\"\n  }\n]"},{"key":"revenue.json","value":"{\n  \"totalFeesUsd\": 0,\n  \"totalSubscriptionUsd\": 87,\n  \"executionCount\": 0,\n  \"lastUpdated\": \"2026-06-22T03:05:26.327Z\"\n}"},{"key":"subscriptions.json","value":"[\n  {\n    \"userAddress\": \"0xSmokeTest000000000000000000000000000001\",\n    \"plan\": \"pro\",\n    \"startedAt\": \"2026-06-22T02:41:50.185Z\",\n    \"expiresAt\": \"2026-07-22T02:41:50.185Z\"\n  },\n  {\n    \"userAddress\": \"0x1A3Fb6EEbee78003d0140ebD4B46Fe0ebd22C45c\",\n    \"plan\": \"pro\",\n    \"startedAt\": \"2026-06-22T03:05:26.324Z\",\n    \"expiresAt\": \"2026-07-22T03:05:26.324Z\"\n  }\n]"},{"key":"watcher-state.json","value":"{\n  \"base:0x7a3f8c2e1b9d4a6f0e8c5b2d1a9f7e4c3b8a6d5e\": 0,\n  \"arbitrum:0x7a3f8c2e1b9d4a6f0e8c5b2d1a9f7e4c3b8a6d5e\": 0\n}"}]